anton_color/__init__.py
anton_color/anton_color.py
anton_color/warna.py
anton_color-0.1.1.dist-info/LICENSE
anton_color-0.1.1.dist-info/METADATA
anton_color-0.1.1.dist-info/WHEEL
anton_color-0.1.1.dist-info/top_level.txt
anton_color-0.1.1.dist-info/RECORD
