Metadata-Version: 2.1
Name: anton_color
Version: 0.1.1
Summary: Modul untuk memberikan warna teks di terminal
Home-page: https://github.com/AntonThomz/color-py
Author: AntonThomzz
Author-email: antonthomzz@gmail.com
Classifier: Programming Language :: Python :: 3
Classifier: License :: OSI Approved :: MIT License
Classifier: Operating System :: OS Independent
Requires-Python: >=3.6
License-File: LICENSE
